fractured_json/FracturedJson.dll
fractured_json/__init__.py
fractured_json/__init__.pyi
fractured_json/__main__.py
fractured_json/_fractured_json.py
fractured_json/_version.py
fractured_json/generated/__init__.py
fractured_json/generated/option_descriptions.py
fractured_json-5.0.0.post5.dist-info/licenses/LICENSE.rst
fractured_json-5.0.0.post5.dist-info/METADATA
fractured_json-5.0.0.post5.dist-info/WHEEL
fractured_json-5.0.0.post5.dist-info/entry_points.txt
fractured_json-5.0.0.post5.dist-info/top_level.txt
fractured_json-5.0.0.post5.dist-info/RECORD
