Metadata-Version: 2.4
Name: fractured-json
Version: 5.0.0.post5
Summary: JSON formatter that produces highly readable but fairly compact output.
Author: Jon Connell
Author-email: Jon Connell <python@figsandfudge.com>
License-Expression: MIT
Project-URL: documentation, https://github.com/masaccio/fractured-json-python/blob/main/README.md
Project-URL: repository, https://github.com/masaccio/fractured-json-python
Classifier: Programming Language :: Python :: 3
Classifier: Programming Language :: C
Classifier: Operating System :: Microsoft :: Windows
Classifier: Operating System :: POSIX :: Linux
Classifier: Operating System :: MacOS
Requires-Python: >=3.11, <3.14
License-File: LICENSE.rst
Requires-Dist: wcwidth>=0.2.8
Requires-Dist: pythonnet>=3.0.5
Requires-Dist: setuptools>=80.9.0
Dynamic: author
Dynamic: license-file
Dynamic: requires-python
